{
  "project_info": {
    "project_number": "930546049097",
    "project_id": "contactos-flutter-e2c23",
    "storage_bucket": "contactos-flutter-e2c23.firebasestorage.app"
  },
  "client": [
    {
      "client_info": {
        "mobilesdk_app_id": "1:930546049097:android:b6765e4ec571dab7159f98",
        "android_client_info": {
          "package_name": "com.contactos.app"
        }
      },
      "oauth_client": [],
      "api_key": [
        {
          "current_key": "AIzaSyANr08VTQ2efBuv9vqDxiGwi_FUrRi7Roc"
        }
      ],
      "services": {
        "appinvite_service": {
          "other_platform_oauth_client": []
        }
      }
    }
  ],
  "configuration_version": "1"
}